ov_helpers/__init__.py
ov_helpers/gradio_helper.py
ov_helpers/notebook_utils.py
ov_helpers/ov_florence2_helper.py
ov_helpers/ov_phi3_vision_helper.py
ov_helpers-0.0.3.dist-info/METADATA
ov_helpers-0.0.3.dist-info/WHEEL
ov_helpers-0.0.3.dist-info/top_level.txt
ov_helpers-0.0.3.dist-info/RECORD
