Metadata-Version: 2.1
Name: ov_helpers
Version: 0.0.3
Summary: OpenVino Helpers
Author: Juan Huertas
Author-email: olonok@hotmail.com
License: MIT
Keywords: python,core package
Classifier: Intended Audience :: Other Audience
Classifier: Programming Language :: Python :: 3
Classifier: Operating System :: POSIX :: Linux
